torelib/__init__.py
torelib/__main__.py
torelib/config.py
torelib-0.1.0.dist-info/METADATA
torelib-0.1.0.dist-info/WHEEL
torelib-0.1.0.dist-info/entry_points.txt
torelib-0.1.0.dist-info/top_level.txt
torelib-0.1.0.dist-info/RECORD
